LICENSE.txt
MANIFEST.in
README.rst
setup.cfg
setup.py
version.txt
docs/AUTHORS.txt
docs/HISTORY.txt
docs/INSTALL.rst
docs/LICENSE.GPL
vnccollab/__init__.py
vnccollab.content.egg-info/PKG-INFO
vnccollab.content.egg-info/SOURCES.txt
vnccollab.content.egg-info/dependency_links.txt
vnccollab.content.egg-info/namespace_packages.txt
vnccollab.content.egg-info/not-zip-safe
vnccollab.content.egg-info/requires.txt
vnccollab.content.egg-info/top_level.txt
vnccollab/content/README.txt
vnccollab/content/__init__.py
vnccollab/content/config.py
vnccollab/content/configure.zcml
vnccollab/content/events.py
vnccollab/content/following.py
vnccollab/content/interfaces.py
vnccollab/content/testing.py
vnccollab/content/userdataschema.py
vnccollab/content/util.py
vnccollab/content/browser/__init__.py
vnccollab/content/browser/author.py
vnccollab/content/browser/configure.zcml
vnccollab/content/browser/following.py
vnccollab/content/browser/interfaces.py
vnccollab/content/browser/css/main.css
vnccollab/content/browser/images/dummy
vnccollab/content/browser/js/main.js
vnccollab/content/browser/templates/author.pt
vnccollab/content/browser/templates/followers_list.pt
vnccollab/content/content/__init__.py
vnccollab/content/content/configure.zcml
vnccollab/content/extender/__init__.py
vnccollab/content/extender/configure.zcml
vnccollab/content/extender/keywords.py
vnccollab/content/form/__init__.py
vnccollab/content/form/configure.zcml
vnccollab/content/form/raptus_autocomplete.py
vnccollab/content/locales/manual.pot
vnccollab/content/locales/vnccollab.content.pot
vnccollab/content/locales/de/LC_MESSAGES/plone.po
vnccollab/content/locales/de/LC_MESSAGES/vnccollab.content.po
vnccollab/content/portlets/__init__.py
vnccollab/content/portlets/configure.zcml
vnccollab/content/portlets/etherpads_list.py
vnccollab/content/portlets/generic_iframe.py
vnccollab/content/portlets/special_rss.py
vnccollab/content/portlets/users_box.py
vnccollab/content/portlets/templates/etherpads_list.pt
vnccollab/content/portlets/templates/generic_iframe.pt
vnccollab/content/portlets/templates/special_rss.pt
vnccollab/content/portlets/templates/users_box.pt
vnccollab/content/profiles/default/browserlayer.xml
vnccollab/content/profiles/default/componentregistry.xml
