Metadata-Version: 1.1
Name: vnccollab.content
Version: 1.5.10
Summary: VNC Collaboration Content Types
Home-page: https://github.com/vnc-biz/vnccollab.content
Author: Vitaliy Podoba
Author-email: vitaliy.podoba@vnc.biz
License: GPL
Keywords: plone content type archetypes vnc
Platform: UNKNOWN
Classifier: Framework :: Plone
Classifier: Intended Audience :: Developers
Classifier: License :: OSI Approved :: GNU General Public License (GPL)
